part3/cpu.v
// Control Unit
module ControlUnit (
    opcode,
    signSelect,
    sourceSelect,
    ALUOP,
    writeEn
);
    // opcode
    input [7:0] opcode;
    // signselect for sub and source select for imidiate, register
    output reg signSelect,sourceSelect;
    // op-code for alu
    output reg [2:0] ALUOP;
    output reg writeEn;

    always @(opcode) begin
        // Loadi 
        if (opcode == 8'b00000000) begin
            #1
            ALUOP = 3'b000;
            signSelect = 1'b0;
            sourceSelect = 1'b1;
            writeEn = 1'b1;
        // mov
        end else if (opcode == 8'b00000001) begin
            #1
            ALUOP = 3'b000;
            signSelect = 1'b0;
            sourceSelect = 1'b0;
            writeEn = 1'b1;
        // add
        end else if (opcode == 8'b00000010) begin
            #1
            ALUOP = 3'b001;
            signSelect = 1'b0;
            sourceSelect = 1'b0;
            writeEn = 1'b1;
        // sub
        end else if (opcode == 8'b00000011) begin
            #1
            ALUOP = 3'b001;
            signSelect = 1'b1;
            sourceSelect = 1'b0;
            writeEn = 1'b1;
        // and
        end else if (opcode == 8'b00000100) begin
            #1
            ALUOP = 3'b010;
            signSelect = 1'b0;
            sourceSelect = 1'b0;
            writeEn = 1'b1;
        // or
        end else if (opcode == 8'b00000101) begin
            #1
            ALUOP = 3'b011;
            signSelect = 1'b0;
            sourceSelect = 1'b0;
            writeEn = 1'b1;
        end else begin
            
        end
    end
    
endmodule

// Program Counter
module pcAdder(PC, PCplus4);
	
	//Declaration of input and output ports
	input [31:0] PC;
	output [31:0] PCplus4;

	//Assign PC+4 value to the output after 1 time unit delay
	assign PCplus4 = PC + 4;
	
endmodule

// module negation
module Negator (
    Input,
    Output
);

input [7:0] Input;
output [7:0] Output;

assign #1 Output = ~Input + 8'b00000001;
    
endmodule

module mux (
    input1,
    input2,
    result,
    select
);

input [7:0] input1,input2;
output reg [7:0] result;
input select;

always @(*) begin
    if (select) begin
        result = input2;
    end else begin
        result = input1;
    end
end
    
endmodule


// Main CPU module
module cpu (
    PC,
    INSTRUCTION,
    CLK,
    RESET
);

// Instruction input
input [31:0] INSTRUCTION;
// input clock and reset
input CLK,RESET;
// output pc to get instruction
output reg [31:0] PC;
wire [31:0] PCout;
// Wires for sign and source select
wire signSelect, sourceSelect;
// Alu opcode wire
wire [2:0] ALUopcode;
// wire for alu result, regout1 and regout2
wire [7:0] ALUres,regout1,regout2;
// mux outputs
wire [7:0] muxNegOut,muxSourceOut;
// negator out
wire [7:0] negOut;
// wire for write enable
wire writeEn;
// wire reg add in
wire [2:0] readreg1,readreg2;

// instantiate control module
ControlUnit control(INSTRUCTION[31:24],signSelect,sourceSelect,ALUopcode,writeEn);
reg_file register(ALUres,regout1,regout2,INSTRUCTION[18:16],INSTRUCTION[10:8],INSTRUCTION[2:0],writeEn,CLK,RESET);
ALU myalu(regout1,muxSourceOut,ALUres,ALUopcode);
Negator neg(regout2,negOut);    
mux muxSrc(muxNegOut,INSTRUCTION[7:0],muxSourceOut,sourceSelect);
mux muxNeg(regout2,negOut,muxNegOut,signSelect);
pcAdder pcadd(PC,PCout);

always @ (posedge CLK)
	begin
		if (RESET == 1'b1) 
		begin
			#1
			PC = 0;		//If RESET signal is HIGH, set PC to zero
		end
		else #1 PC = PCout;		//Else, write new PC value
	end

endmodule

part3/alu.v
// Forward Function
module FORWARD (
    DATA1,
    DATA2,
    RESULT
);
    // Define Inputs
    input [7:0] DATA1, DATA2;
    // Define Outputs
    output reg [7:0] RESULT;

    always @(DATA1, DATA2) begin
        #1
        RESULT = DATA2; 
    end
    
endmodule


// bitvise AND
module AND (
    DATA1,
    DATA2,
    RESULT
);

    // Define Inputs
    input [7:0] DATA1, DATA2;
    // Define Outputs
    output reg [7:0] RESULT;

    always @(DATA1, DATA2) begin  
        #1      
        RESULT = DATA1 & DATA2;
    end
    
endmodule

// Bitwise OR
module OR (
    DATA1,
    DATA2,
    RESULT
);

    // Define Inputs
    input [7:0] DATA1, DATA2;
    // Define Outputs
    output reg [7:0] RESULT;

    always @(DATA1, DATA2) begin
        #1
        RESULT = DATA1 | DATA2;
    end
    
endmodule

// Module ADD
module ADD (
    DATA1,
    DATA2,
    RESULT
);

    // Define Inputs
    input [7:0] DATA1, DATA2;
    // Define Outputs
    output reg [7:0] RESULT;

    always @(DATA1, DATA2) begin
        #2
        RESULT = DATA1 + DATA2;
    end
    
endmodule

module ALU (
    DATA1,
    DATA2,
    RESULT,
    SELECT
);
    // Define Inputs
    input [7:0] DATA1,DATA2;
    input [2:0] SELECT;
    // Define Output
    output reg [7:0] RESULT;
    wire [7:0] wire1,wire2,wire3,wire4;
    
    FORWARD forward1(DATA1,DATA2,wire1);            
    ADD add1(DATA1,DATA2,wire2);            
    AND and1(DATA1,DATA2,wire3);            
    OR or1(DATA1,DATA2,wire4);  

    always @(SELECT) begin
        case (SELECT)
            3'b000: assign RESULT = wire1;
            3'b001: assign RESULT = wire2;
            3'b010: assign RESULT = wire3;
            3'b011: assign RESULT = wire4;
        endcase
    end    

endmodule

module stimulus;
    reg [7:0] DATA1, DATA2;
    reg [2:0] SELECT;
    wire [7:0] RESULT;

    ALU alu1(DATA1,DATA2,RESULT,SELECT);

    initial begin
        DATA1 = 8'b00001111;
        DATA2 = 8'b01100001;
        SELECT = 3'b000;
        #5
        $display("%b for %b = %b", DATA1, DATA2, RESULT);

        DATA1 = 8'b00001111;
        DATA2 = 8'b00001001;
        SELECT = 3'b001;
        #2
        $display("%b + %b = %b", DATA1, DATA2, RESULT);

        DATA1 = 8'b00001111;
        DATA2 = 8'b01011001;
        SELECT = 3'b010;
        #2
        $display("%b and %b = %b", DATA1, DATA2, RESULT);

        DATA1 = 8'b00001111;
        DATA2 = 8'b00111001;
        SELECT = 3'b011;
        #2
        $display("%b or %b = %b", DATA1, DATA2, RESULT);
    end

endmodule

part2/reg.v
module reg_file(IN, OUT1, OUT2, INADDRESS, OUT1ADDRESS, OUT2ADDRESS, WRITE, CLK, RESET);
    // Declare input
    input [7:0] IN;
	input [2:0] INADDRESS, OUT1ADDRESS, OUT2ADDRESS;
	input WRITE, CLK, RESET;
    // Declare output
	output [7:0] OUT1, OUT2;
	
	
	
	// 8 x 8 register
	reg [7:0] REGISTER [7:0];

	//iterative variable
	integer i;
	
	
	//assigning the outputs
	assign #2 OUT1 = REGISTER[OUT1ADDRESS];		//assign the value that storesd in OUT1ADDRESS
	assign #2 OUT2 = REGISTER[OUT2ADDRESS];		//assign the value that storesd in OUT2ADDRESS
	
	
	always @ (posedge CLK)
	begin
		if (RESET == 1'b1)		
		begin		
			for (i = 0; i < 8; i = i + 1)			
			begin
				REGISTER[i] = 8'b00000000;		
			end			
		end
		else if (WRITE == 1'b1)			
		begin		
			#1 REGISTER[INADDRESS] = IN;			
		end		
	end	
endmodule

part3/CPU Programming Tools-20230521/cpu_tb.v
// Computer Architecture (CO224) - Lab 05
// Design: Testbench of Integrated CPU of Simple Processor
// Author: Isuru Nawinne
module cpu_tb;

    reg CLK, RESET;
    wire [31:0] PC;
    wire [31:0] INSTRUCTION;
    
    /* 
    ------------------------
     SIMPLE INSTRUCTION MEM
    ------------------------
    */
    
    // TODO: Initialize an array of registers (8x1024) named 'instr_mem' to be used as instruction memory
    reg [7:0] instr_mem [1023:0];
    
    // TODO: Create combinational logic to support CPU instruction fetching, given the Program Counter(PC) value 
    //       (make sure you include the delay for instruction fetching here)
    assign #2 INSTRUCTION = {instr_mem[PC+3], instr_mem[PC+2], instr_mem[PC+1], instr_mem[PC]};
    
    initial
    begin
        // Initialize instruction memory with the set of instructions you need execute on CPU
        
        // METHOD 1: manually loading instructions to instr_mem
        //{instr_mem[10'd3], instr_mem[10'd2], instr_mem[10'd1], instr_mem[10'd0]} = 32'b00000000000001000000000000000101;
        //{instr_mem[10'd7], instr_mem[10'd6], instr_mem[10'd5], instr_mem[10'd4]} = 32'b00000000000000100000000000001001;
        //{instr_mem[10'd11], instr_mem[10'd10], instr_mem[10'd9], instr_mem[10'd8]} = 32'b00000010000001100000010000000010;
        
        // METHOD 2: loading instr_mem content from instr_mem.mem file
        $readmemb("programmer/instr_mem.mem", instr_mem);
    end
    
    /* 
    -----
     CPU
    -----
    */
    cpu mycpu(PC, INSTRUCTION, CLK, RESET);

    initial
    begin
    
        // generate files needed to plot the waveform using GTKWave
        $dumpfile("cpu_wavedata.vcd");
		$dumpvars(0, cpu_tb);
        
        CLK = 1'b0;
        RESET = 1'b1;
        
        // TODO: Reset the CPU (by giving a pulse to RESET signal) to start the program execution
        #5
        RESET = 1'b0;
        // finish simulation after some time
        #500
        $finish;
    end
    
    // clock signal generation
    always
        #4 CLK = ~CLK;
        

endmodule

part3/cpu_wavedata.vcd
$date
	Wed May 31 10:33:19 2023
$end
$version
	Icarus Verilog
$end
$timescale
	1s
$end
$scope module cpu_tb $end
$var wire 32 ! PC [31:0] $end
$var wire 32 " INSTRUCTION [31:0] $end
$var reg 1 # CLK $end
$var reg 1 $ RESET $end
$scope module mycpu $end
$var wire 1 # CLK $end
$var wire 32 % INSTRUCTION [31:0] $end
$var wire 1 $ RESET $end
$var wire 1 & writeEn $end
$var wire 1 ' sourceSelect $end
$var wire 1 ( signSelect $end
$var wire 8 ) regout2 [7:0] $end
$var wire 8 * regout1 [7:0] $end
$var wire 8 + negOut [7:0] $end
$var wire 8 , muxSourceOut [7:0] $end
$var wire 8 - muxNegOut [7:0] $end
$var wire 32 . PCout [31:0] $end
$var wire 8 / ALUres [7:0] $end
$var wire 3 0 ALUopcode [2:0] $end
$var reg 32 1 PC [31:0] $end
$scope module control $end
$var wire 8 2 opcode [7:0] $end
$var reg 3 3 ALUOP [2:0] $end
$var reg 1 ( signSelect $end
$var reg 1 ' sourceSelect $end
$var reg 1 & writeEn $end
$upscope $end
$scope module muxNeg $end
$var wire 1 ( select $end
$var wire 8 4 input2 [7:0] $end
$var wire 8 5 input1 [7:0] $end
$var reg 8 6 result [7:0] $end
$upscope $end
$scope module muxSrc $end
$var wire 8 7 input1 [7:0] $end
$var wire 8 8 input2 [7:0] $end
$var wire 1 ' select $end
$var reg 8 9 result [7:0] $end
$upscope $end
$scope module myalu $end
$var wire 8 : DATA2 [7:0] $end
$var wire 3 ; SELECT [2:0] $end
$var wire 8 < wire4 [7:0] $end
$var wire 8 = wire3 [7:0] $end
$var wire 8 > wire2 [7:0] $end
$var wire 8 ? wire1 [7:0] $end
$var wire 8 @ DATA1 [7:0] $end
$var reg 8 A RESULT [7:0] $end
$scope module add1 $end
$var wire 8 B DATA2 [7:0] $end
$var wire 8 C DATA1 [7:0] $end
$var reg 8 D RESULT [7:0] $end
$upscope $end
$scope module and1 $end
$var wire 8 E DATA2 [7:0] $end
$var wire 8 F DATA1 [7:0] $end
$var reg 8 G RESULT [7:0] $end
$upscope $end
$scope module forward1 $end
$var wire 8 H DATA2 [7:0] $end
$var wire 8 I DATA1 [7:0] $end
$var reg 8 J RESULT [7:0] $end
$upscope $end
$scope module or1 $end
$var wire 8 K DATA2 [7:0] $end
$var wire 8 L DATA1 [7:0] $end
$var reg 8 M RESULT [7:0] $end
$upscope $end
$upscope $end
$scope module neg $end
$var wire 8 N Output [7:0] $end
$var wire 8 O Input [7:0] $end
$upscope $end
$scope module pcadd $end
$var wire 32 P PC [31:0] $end
$var wire 32 Q PCplus4 [31:0] $end
$upscope $end
$scope module register $end
$var wire 1 # CLK $end
$var wire 8 R IN [7:0] $end
$var wire 3 S INADDRESS [2:0] $end
$var wire 8 T OUT1 [7:0] $end
$var wire 3 U OUT1ADDRESS [2:0] $end
$var wire 8 V OUT2 [7:0] $end
$var wire 3 W OUT2ADDRESS [2:0] $end
$var wire 1 $ RESET $end
$var wire 1 & WRITE $end
$var integer 32 X i [31:0] $end
$upscope $end
$upscope $end
$upscope $end
$enddefinitions $end
#0
$dumpvars
bx X
bx W
bx V
bx U
bx T
bx S
bx R
bx Q
bx P
bx O
bx N
bx M
bx L
bx K
bx J
bx I
bx H
bx G
bx F
bx E
bx D
bx C
bx B
bx A
bx @
bx ?
bx >
bx =
bx <
bx ;
bx :
bx 9
bx 8
bx 7
bx 6
bx 5
bx 4
bx 3
bx 2
bx 1
bx 0
bx /
bx .
bx -
bx ,
bx +
bx *
bx )
x(
x'
x&
bx %
1$
0#
bx "
bx !
$end
#4
b1000 X
1#
#5
b100 .
b100 Q
b0 !
b0 1
b0 P
0$
#7
b0 2
b0 S
b0 U
b101 W
b101 8
b101 "
b101 %
#8
b101 ,
b101 9
b101 :
b101 B
b101 E
b101 H
b101 K
1&
1'
0(
b0 0
b0 3
b0 ;
0#
#9
b0 -
b0 6
b0 7
b101 <
b101 M
b0 =
b0 G
b101 /
b101 A
b101 R
b101 ?
b101 J
b0 *
b0 @
b0 C
b0 F
b0 I
b0 L
b0 T
b0 )
b0 5
b0 O
b0 V
#10
b0 +
b0 4
b0 N
b101 >
b101 D
#12
1#
#13
b1000 .
b1000 Q
b100 !
b100 1
b100 P
#15
b1001 ,
b1001 9
b1001 :
b1001 B
b1001 E
b1001 H
b1001 K
b1 S
b1 W
b1001 8
b101 *
b101 @
b101 C
b101 F
b101 I
b101 L
b101 T
b10000000000001001 "
b10000000000001001 %
#16
b1001 /
b1001 A
b1001 R
b1001 ?
b1001 J
b1 =
b1 G
b1101 <
b1101 M
0#
#17
b1110 >
b1110 D
#20
1#
#21
b1100 .
b1100 Q
b1000 !
b1000 1
b1000 P
#23
b1 ,
b1 9
b1 :
b1 B
b1 E
b1 H
b1 K
b1 2
b10 S
b1 8
b1001 -
b1001 6
b1001 7
b1000000100000000000000001 "
b1000000100000000000000001 %
b1001 )
b1001 5
b1001 O
b1001 V
#24
b1001 ,
b1001 9
b1001 :
b1001 B
b1001 E
b1001 H
b1001 K
b101 <
b101 M
b1 /
b1 A
b1 R
b1 ?
b1 J
0'
b11110111 +
b11110111 4
b11110111 N
0#
#25
b1001 /
b1001 A
b1001 R
b1001 ?
b1001 J
b1101 <
b1101 M
#28
1#
#29
b10000 .
b10000 Q
b1100 !
b1100 1
b1100 P
#31
b10 2
b11 S
b10 U
b0 W
b0 8
b10000000110000001000000000 "
b10000000110000001000000000 %
#32
b1110 /
b1110 A
b1110 R
b1 0
b1 3
b1 ;
0#
#33
b101 ,
b101 9
b101 :
b101 B
b101 E
b101 H
b101 K
b101 -
b101 6
b101 7
b1001 *
b1001 @
b1001 C
b1001 F
b1001 I
b1001 L
b1001 T
b101 )
b101 5
b101 O
b101 V
#34
b101 ?
b101 J
b11111011 +
b11111011 4
b11111011 N
#36
1#
#37
b10100 .
b10100 Q
b10000 !
b10000 1
b10000 P
#39
b11 2
b100 S
b11 U
b1 W
b1 8
b11000001000000001100000001 "
b11000001000000001100000001 %
#40
b11111011 ,
b11111011 9
b11111011 :
b11111011 B
b11111011 E
b11111011 H
b11111011 K
b11111011 -
b11111011 6
b11111011 7
1(
0#
#41
b11111011 ?
b11111011 J
b1010 =
b1010 G
b11111111 <
b11111111 M
b1110 *
b1110 @
b1110 C
b1110 F
b1110 I
b1110 L
b1110 T
b1001 )
b1001 5
b1001 O
b1001 V
#42
b11110111 ,
b11110111 9
b11110111 :
b11110111 B
b11110111 E
b11110111 H
b11110111 K
b11110111 -
b11110111 6
b11110111 7
b11110111 +
b11110111 4
b11110111 N
b1001 /
b1001 A
b1001 R
b1001 >
b1001 D
#43
b110 =
b110 G
b11110111 ?
b11110111 J
#44
b101 /
b101 A
b101 R
b101 >
b101 D
1#
#45
b11000 .
b11000 Q
b10100 !
b10100 1
b10100 P
#47
b0 2
b0 S
b0 U
b101 W
b1110101 8
b1110101 "
b1110101 %
#48
b1110101 ,
b1110101 9
b1110101 :
b1110101 B
b1110101 E
b1110101 H
b1110101 K
b1001 -
b1001 6
b1001 7
b11110111 /
b11110111 A
b11110111 R
1'
0(
b0 0
b0 3
b0 ;
0#
#49
b0 -
b0 6
b0 7
b1110101 /
b1110101 A
b1110101 R
b1110101 ?
b1110101 J
b101 =
b101 G
b1110101 <
b1110101 M
b101 *
b101 @
b101 C
b101 F
b101 I
b101 L
b101 T
b0 )
b0 5
b0 O
b0 V
#50
b0 +
b0 4
b0 N
b1111010 >
b1111010 D
#52
1#
#53
b11100 .
b11100 Q
b11000 !
b11000 1
b11000 P
#55
b10010010 ,
b10010010 9
b10010010 :
b10010010 B
b10010010 E
b10010010 H
b10010010 K
b1 S
b10 W
b10010010 8
b10000000010010010 "
b10000000010010010 %
b1110101 *
b1110101 @
b1110101 C
b1110101 F
b1110101 I
b1110101 L
b1110101 T
#56
b11110111 <
b11110111 M
b10000 =
b10000 G
b10010010 /
b10010010 A
b10010010 R
b10010010 ?
b10010010 J
0#
#57
b1001 -
b1001 6
b1001 7
b1001 )
b1001 5
b1001 O
b1001 V
b111 >
b111 D
#58
b11110111 +
b11110111 4
b11110111 N
#60
1#
#61
b100000 .
b100000 Q
b11100 !
b11100 1
b11100 P
#63
b0 ,
b0 9
b0 :
b0 B
b0 E
b0 H
b0 K
b100 2
b101 S
b1 U
b0 W
b0 8
b100000001010000000100000000 "
b100000001010000000100000000 %
#64
b1001 ,
b1001 9
b1001 :
b1001 B
b1001 E
b1001 H
b1001 K
b0 /
b0 A
b0 R
b0 ?
b0 J
b0 =
b0 G
b1110101 <
b1110101 M
0'
b10 0
b10 3
b10 ;
0#
#65
b1110101 ,
b1110101 9
b1110101 :
b1110101 B
b1110101 E
b1110101 H
b1110101 K
b1110101 -
b1110101 6
b1110101 7
b10011011 <
b10011011 M
b1001 ?
b1001 J
b10011011 >
b10011011 D
b10010010 *
b10010010 @
b10010010 C
b10010010 F
b10010010 I
b10010010 L
b10010010 T
b1110101 )
b1110101 5
b1110101 O
b1110101 V
#66
b1110101 ?
b1110101 J
b10000 /
b10000 A
b10000 R
b10000 =
b10000 G
b11110111 <
b11110111 M
b10001011 +
b10001011 4
b10001011 N
#67
b111 >
b111 D
#68
1#
#69
b100100 .
b100100 Q
b100000 !
b100000 1
b100000 P
#71
b101 2
b110 S
b101 U
b10 W
b10 8
b101000001100000010100000010 "
b101000001100000010100000010 %
#72
b11110111 /
b11110111 A
b11110111 R
b11 0
b11 3
b11 ;
0#
#73
b1001 ,
b1001 9
b1001 :
b1001 B
b1001 E
b1001 H
b1001 K
b1001 -
b1001 6
b1001 7
b10000 *
b10000 @
b10000 C
b10000 F
b10000 I
b10000 L
b10000 T
b1001 )
b1001 5
b1001 O
b1001 V
#74
b11001 /
b11001 A
b11001 R
b11001 <
b11001 M
b0 =
b0 G
b1001 ?
b1001 J
b11110111 +
b11110111 4
b11110111 N
#75
b11001 >
b11001 D
#76
1#
#77
b101000 .
b101000 Q
b100100 !
b100100 1
b100100 P
#79
bx 2
bx S
bx U
bx W
bx 8
bx "
bx %
#80
0#
#81
bx ,
bx 9
bx :
bx B
bx E
bx H
bx K
bx -
bx 6
bx 7
bx *
bx @
bx C
bx F
bx I
bx L
bx T
bx )
bx 5
bx O
bx V
#82
bx ?
bx J
bx =
bx G
bx /
bx A
bx R
bx <
bx M
bx +
bx 4
bx N
#83
bx >
bx D
#84
1#
#85
b101100 .
b101100 Q
b101000 !
b101000 1
b101000 P
#88
0#
#92
1#
#93
b110000 .
b110000 Q
b101100 !
b101100 1
b101100 P
#96
0#
#100
1#
#101
b110100 .
b110100 Q
b110000 !
b110000 1
b110000 P
#104
0#
#108
1#
#109
b111000 .
b111000 Q
b110100 !
b110100 1
b110100 P
#112
0#
#116
1#
#117
b111100 .
b111100 Q
b111000 !
b111000 1
b111000 P
#120
0#
#124
1#
#125
b1000000 .
b1000000 Q
b111100 !
b111100 1
b111100 P
#128
0#
#132
1#
#133
b1000100 .
b1000100 Q
b1000000 !
b1000000 1
b1000000 P
#136
0#
#140
1#
#141
b1001000 .
b1001000 Q
b1000100 !
b1000100 1
b1000100 P
#144
0#
#148
1#
#149
b1001100 .
b1001100 Q
b1001000 !
b1001000 1
b1001000 P
#152
0#
#156
1#
#157
b1010000 .
b1010000 Q
b1001100 !
b1001100 1
b1001100 P
#160
0#
#164
1#
#165
b1010100 .
b1010100 Q
b1010000 !
b1010000 1
b1010000 P
#168
0#
#172
1#
#173
b1011000 .
b1011000 Q
b1010100 !
b1010100 1
b1010100 P
#176
0#
#180
1#
#181
b1011100 .
b1011100 Q
b1011000 !
b1011000 1
b1011000 P
#184
0#
#188
1#
#189
b1100000 .
b1100000 Q
b1011100 !
b1011100 1
b1011100 P
#192
0#
#196
1#
#197
b1100100 .
b1100100 Q
b1100000 !
b1100000 1
b1100000 P
#200
0#
#204
1#
#205
b1101000 .
b1101000 Q
b1100100 !
b1100100 1
b1100100 P
#208
0#
#212
1#
#213
b1101100 .
b1101100 Q
b1101000 !
b1101000 1
b1101000 P
#216
0#
#220
1#
#221
b1110000 .
b1110000 Q
b1101100 !
b1101100 1
b1101100 P
#224
0#
#228
1#
#229
b1110100 .
b1110100 Q
b1110000 !
b1110000 1
b1110000 P
#232
0#
#236
1#
#237
b1111000 .
b1111000 Q
b1110100 !
b1110100 1
b1110100 P
#240
0#
#244
1#
#245
b1111100 .
b1111100 Q
b1111000 !
b1111000 1
b1111000 P
#248
0#
#252
1#
#253
b10000000 .
b10000000 Q
b1111100 !
b1111100 1
b1111100 P
#256
0#
#260
1#
#261
b10000100 .
b10000100 Q
b10000000 !
b10000000 1
b10000000 P
#264
0#
#268
1#
#269
b10001000 .
b10001000 Q
b10000100 !
b10000100 1
b10000100 P
#272
0#
#276
1#
#277
b10001100 .
b10001100 Q
b10001000 !
b10001000 1
b10001000 P
#280
0#
#284
1#
#285
b10010000 .
b10010000 Q
b10001100 !
b10001100 1
b10001100 P
#288
0#
#292
1#
#293
b10010100 .
b10010100 Q
b10010000 !
b10010000 1
b10010000 P
#296
0#
#300
1#
#301
b10011000 .
b10011000 Q
b10010100 !
b10010100 1
b10010100 P
#304
0#
#308
1#
#309
b10011100 .
b10011100 Q
b10011000 !
b10011000 1
b10011000 P
#312
0#
#316
1#
#317
b10100000 .
b10100000 Q
b10011100 !
b10011100 1
b10011100 P
#320
0#
#324
1#
#325
b10100100 .
b10100100 Q
b10100000 !
b10100000 1
b10100000 P
#328
0#
#332
1#
#333
b10101000 .
b10101000 Q
b10100100 !
b10100100 1
b10100100 P
#336
0#
#340
1#
#341
b10101100 .
b10101100 Q
b10101000 !
b10101000 1
b10101000 P
#344
0#
#348
1#
#349
b10110000 .
b10110000 Q
b10101100 !
b10101100 1
b10101100 P
#352
0#
#356
1#
#357
b10110100 .
b10110100 Q
b10110000 !
b10110000 1
b10110000 P
#360
0#
#364
1#
#365
b10111000 .
b10111000 Q
b10110100 !
b10110100 1
b10110100 P
#368
0#
#372
1#
#373
b10111100 .
b10111100 Q
b10111000 !
b10111000 1
b10111000 P
#376
0#
#380
1#
#381
b11000000 .
b11000000 Q
b10111100 !
b10111100 1
b10111100 P
#384
0#
#388
1#
#389
b11000100 .
b11000100 Q
b11000000 !
b11000000 1
b11000000 P
#392
0#
#396
1#
#397
b11001000 .
b11001000 Q
b11000100 !
b11000100 1
b11000100 P
#400
0#
#404
1#
#405
b11001100 .
b11001100 Q
b11001000 !
b11001000 1
b11001000 P
#408
0#
#412
1#
#413
b11010000 .
b11010000 Q
b11001100 !
b11001100 1
b11001100 P
#416
0#
#420
1#
#421
b11010100 .
b11010100 Q
b11010000 !
b11010000 1
b11010000 P
#424
0#
#428
1#
#429
b11011000 .
b11011000 Q
b11010100 !
b11010100 1
b11010100 P
#432
0#
#436
1#
#437
b11011100 .
b11011100 Q
b11011000 !
b11011000 1
b11011000 P
#440
0#
#444
1#
#445
b11100000 .
b11100000 Q
b11011100 !
b11011100 1
b11011100 P
#448
0#
#452
1#
#453
b11100100 .
b11100100 Q
b11100000 !
b11100000 1
b11100000 P
#456
0#
#460
1#
#461
b11101000 .
b11101000 Q
b11100100 !
b11100100 1
b11100100 P
#464
0#
#468
1#
#469
b11101100 .
b11101100 Q
b11101000 !
b11101000 1
b11101000 P
#472
0#
#476
1#
#477
b11110000 .
b11110000 Q
b11101100 !
b11101100 1
b11101100 P
#480
0#
#484
1#
#485
b11110100 .
b11110100 Q
b11110000 !
b11110000 1
b11110000 P
#488
0#
#492
1#
#493
b11111000 .
b11111000 Q
b11110100 !
b11110100 1
b11110100 P
#496
0#
#500
1#
#501
b11111100 .
b11111100 Q
b11111000 !
b11111000 1
b11111000 P
