part5/cpu.v
// Control Unit
module ControlUnit (
    opcode,
    signSelect,
    sourceSelect,
    jumpSelect,
    eqSelect,
    neqSelect,
    ALUOP,
    writeEn
);
    // opcode
    input [7:0] opcode;
    // signselect for sub and source select for imidiate, register
    output reg signSelect,sourceSelect,jumpSelect,eqSelect,neqSelect;
    // op-code for alu
    output reg [2:0] ALUOP;
    output reg writeEn;

    always @(opcode) begin
        // Loadi 
        if (opcode == 8'b00000000) begin
            #1
            ALUOP = 3'b000;
            signSelect = 1'b0;
            sourceSelect = 1'b1;
            writeEn = 1'b1;
            jumpSelect = 1'b0;
            eqSelect = 1'b0;
            neqSelect = 1'b0;
        // mov
        end else if (opcode == 8'b00000001) begin
            #1
            ALUOP = 3'b000;
            signSelect = 1'b0;
            sourceSelect = 1'b0;
            writeEn = 1'b1;
            jumpSelect = 1'b0;
            eqSelect = 1'b0;
            neqSelect = 1'b0;
        // add
        end else if (opcode == 8'b00000010) begin
            #1
            ALUOP = 3'b001;
            signSelect = 1'b0;
            sourceSelect = 1'b0;
            writeEn = 1'b1;
            jumpSelect = 1'b0;
            eqSelect = 1'b0;
            neqSelect = 1'b0;
        // sub
        end else if (opcode == 8'b00000011) begin
            #1
            ALUOP = 3'b001;
            signSelect = 1'b1;
            sourceSelect = 1'b0;
            writeEn = 1'b1;
            jumpSelect = 1'b0;
            eqSelect = 1'b0;
            neqSelect = 1'b0;
        // and
        end else if (opcode == 8'b00000100) begin
            #1
            ALUOP = 3'b010;
            signSelect = 1'b0;
            sourceSelect = 1'b0;
            writeEn = 1'b1;
            jumpSelect = 1'b0;
            eqSelect = 1'b0;
            neqSelect = 1'b0;
        // or
        end else if (opcode == 8'b00000101) begin
            #1
            ALUOP = 3'b011;
            signSelect = 1'b0;
            sourceSelect = 1'b0;
            writeEn = 1'b1;
            jumpSelect = 1'b0;
            eqSelect = 1'b0;
            neqSelect = 1'b0;
        // j
        end else if (opcode == 8'b00000110) begin
            #1
            ALUOP = 3'b000;
            signSelect = 1'b0;
            sourceSelect = 1'b0;
            writeEn = 1'b0;
            jumpSelect = 1'b1;
            eqSelect = 1'b0;
            neqSelect = 1'b0;
        // beq
        end else if (opcode == 8'b00000111) begin
            #1
            ALUOP = 3'b111;
            signSelect = 1'b1;
            sourceSelect = 1'b0;
            writeEn = 1'b0;
            jumpSelect = 1'b0;
            eqSelect = 1'b1;
            neqSelect = 1'b0;
        // bne
        end else if (opcode == 8'b00001000) begin
            #1
            ALUOP = 3'b111;
            signSelect = 1'b1;
            sourceSelect = 1'b0;
            writeEn = 1'b0;
            jumpSelect = 1'b0;
            eqSelect = 1'b0;
            neqSelect = 1'b1;
        // sll,srl,sla,sra,rol,ror
        end else if (opcode == 8'b00001001) begin
            #1
            ALUOP = 3'b100;
            signSelect = 1'b0;
            sourceSelect = 1'b1;
            writeEn = 1'b1;
            jumpSelect = 1'b0;
            eqSelect = 1'b0;
            neqSelect = 1'b0;
        end else begin
            
        end
    end
    
endmodule

// Program Counter
module pcAdder(PC, PCplus4);
	
	//Declaration of input and output ports
	input [31:0] PC;
	output [31:0] PCplus4;

	//Assign PC+4 value to the output after 1 time unit delay
	assign PCplus4 = PC + 4;
	
endmodule

// module negation
module Negator (
    Input,
    Output
);

input [7:0] Input;
output [7:0] Output;

assign #1 Output = ~Input + 8'b00000001;
    
endmodule

module mux (
    input1,
    input2,
    result,
    select
);

input [7:0] input1,input2;
output reg [7:0] result;
input select;

always @(*) begin
    if (select) begin
        result = input2;
    end else begin
        result = input1;
    end
end
    
endmodule

module muxPC (
    input1,
    input2,
    result,
    jumpSelect,
    Zero,
    eqSelect,
    neqselect
);

input [31:0] input1,input2;
output reg [31:0] result;
input jumpSelect,Zero,eqSelect,neqselect;

always @(*) begin
    if (jumpSelect || Zero && eqSelect || ~Zero && neqselect) begin
        result = input2;
    end else begin
        result = input1;
    end
end
    
endmodule

// branch adder
module branchAdder (
    currPC,
    offset,
    finalPC
);

input [31:0] currPC, offset;
output [31:0] finalPC;

assign finalPC = currPC + offset;
    
endmodule

// sign extender
module SignExtender (
    short,
    long
);

input [7:0] short;
output [31:0] long;

assign long = {{24{short[7]}}, short} << 2;
    
endmodule

// Main CPU module
module cpu (
    PC,
    INSTRUCTION,
    CLK,
    RESET
);

// Instruction input
input [31:0] INSTRUCTION;
// input clock and reset
input CLK,RESET;
// output pc to get instruction
output reg [31:0] PC;
wire [31:0] PCout;
// Wires for sign and source select
wire signSelect, sourceSelect, jumpSelect, eqSelect, neqSelect;
// Alu opcode wire
wire [2:0] ALUopcode;
// wire for alu result, regout1 and regout2
wire [7:0] ALUres,regout1,regout2;
// mux outputs
wire [7:0] muxNegOut,muxSourceOut;
// negator out
wire [7:0] negOut;
// wire for write enable
wire writeEn;
// wire reg add in
wire [2:0] readreg1,readreg2;
// Extended value
wire [31:0] extendedValue;
// Jumped pc value
wire [31:0] jumpedPC, finalPC;
// alu zero output
wire Zero;

// instantiate control module
ControlUnit control(INSTRUCTION[31:24],signSelect,sourceSelect,jumpSelect,eqSelect,neqSelect,ALUopcode,writeEn);
reg_file register(ALUres,regout1,regout2,INSTRUCTION[18:16],INSTRUCTION[10:8],INSTRUCTION[2:0],writeEn,CLK,RESET);
ALU myalu(regout1,muxSourceOut,ALUres,ALUopcode,Zero);
Negator neg(regout2,negOut);    
mux muxSrc(muxNegOut,INSTRUCTION[7:0],muxSourceOut,sourceSelect);
mux muxNeg(regout2,negOut,muxNegOut,signSelect);
pcAdder pcadd(PC,PCout);
branchAdder badder(PCout, extendedValue, jumpedPC);
SignExtender signext(INSTRUCTION[23:16], extendedValue);
muxPC jump(PCout, jumpedPC, finalPC, jumpSelect, Zero, eqSelect, neqSelect);

always @ (posedge CLK)
	begin
		if (RESET == 1'b1) 
		begin
			#1
			PC = 0;		//If RESET signal is HIGH, set PC to zero
		end
		else #1 PC = finalPC;		//Else, write new PC value
	end

endmodule

part7/alu.v
`timescale  1ns/100ps

// Forward Function
module FORWARD (
    DATA1,
    DATA2,
    RESULT
);
    // Define Inputs
    input [7:0] DATA1, DATA2;
    // Define Outputs
    output reg [7:0] RESULT;

    always @(DATA1, DATA2) begin
        #1
        RESULT = DATA2; 
    end
    
endmodule


// bitvise AND
module AND (
    DATA1,
    DATA2,
    RESULT
);

    // Define Inputs
    input [7:0] DATA1, DATA2;
    // Define Outputs
    output reg [7:0] RESULT;

    always @(DATA1, DATA2) begin  
        #1      
        RESULT = DATA1 & DATA2;
    end
    
endmodule

// Bitwise OR
module OR (
    DATA1,
    DATA2,
    RESULT
);

    // Define Inputs
    input [7:0] DATA1, DATA2;
    // Define Outputs
    output reg [7:0] RESULT;

    always @(DATA1, DATA2) begin
        #1
        RESULT = DATA1 | DATA2;
    end
    
endmodule

// Module ADD
module ADD (
    DATA1,
    DATA2,
    RESULT
);

    // Define Inputs
    input [7:0] DATA1, DATA2;
    // Define Outputs
    output reg [7:0] RESULT;

    always @(DATA1, DATA2) begin
        #2
        RESULT = DATA1 + DATA2;
    end
    
endmodule

module LeftShift (
    in,
    out,
    shift
);

    input [7:0] in;
    input [2:0] shift;
    output [7:0] out;

    reg [7:0] result;

    always @(*) begin
        case (shift)
            3'b000: result = in; // No shift
            3'b001: result = {in[6:0], 1'b0}; // Shift left by 1 bit
            3'b010: result = {in[5:0], 2'b0}; // Shift left by 2 bits
            3'b011: result = {in[4:0], 3'b0}; // Shift left by 3 bits
            3'b100: result = {in[3:0], 4'b0}; // Shift left by 4 bits
            3'b101: result = {in[2:0], 5'b0}; // Shift left by 5 bits
            3'b110: result = {in[1:0], 6'b0}; // Shift left by 6 bits
            3'b111: result = {in[0], 7'b0}; // Shift left by 7 bits
            default: result = in; // No shift (default case)
        endcase
    end

    // this will need 3 of 2to1 mux levels. so #1 for each and give #3 delay
    assign #3 out = result;

endmodule

module RightShift (
    in,
    out,
    shift
);
    
    input [7:0] in;
    input [2:0] shift;
    output [7:0] out;
    
    reg [7:0] result;

    always @(*) begin
        case (shift)
            3'b000: result = in; // No shift
            3'b001: result = {1'b0, in[7:1]}; // Shift right by 1 bit
            3'b010: result = {2'b0, in[7:2]}; // Shift right by 2 bits
            3'b011: result = {3'b0, in[7:3]}; // Shift right by 3 bits
            3'b100: result = {4'b0, in[7:4]}; // Shift right by 4 bits
            3'b101: result = {5'b0, in[7:5]}; // Shift right by 5 bits
            3'b110: result = {6'b0, in[7:6]}; // Shift right by 6 bits
            3'b111: result = {7'b0, in[7]}; // Shift right by 7 bits
            default: result = in; // No shift (default case)
        endcase
    end

    // this will need 3 of 2to1 mux levels. so #1 for each and give #3 delay
    assign #3 out = result;

endmodule

module LeftShiftArith (
    in,
    out,
    shift
);

    input [7:0] in;
    input [2:0] shift;
    output [7:0] out;

    reg [7:0] result;

    always @(*) begin
        case (shift)
            3'b000: result = in; // No shift
            3'b001: result = {in[7], in[5:0], 1'b0}; // Shift left by 1 bit
            3'b010: result = {in[7], in[4:0], 2'b0}; // Shift left by 2 bits
            3'b011: result = {in[7], in[3:0], 3'b0}; // Shift left by 3 bits
            3'b100: result = {in[7], in[2:0], 4'b0}; // Shift left by 4 bits
            3'b101: result = {in[7], in[1:0], 5'b0}; // Shift left by 5 bits
            3'b110: result = {in[7], in[0], 6'b0}; // Shift left by 6 bits
            3'b111: result = {in[7], 7'b0}; // Shift left by 7 bits
            default: result = in; // No shift (default case)
        endcase
    end

    // this will need 3 of 2to1 mux levels. so #1 for each and give #3 delay
    assign #3 out = result;

endmodule

module RightShiftArith (
    in,
    out,
    shift
);
    
    input [7:0] in;
    input [2:0] shift;
    output [7:0] out;
    
    reg [7:0] result;

    always @(*) begin
        case (shift)
            3'b000: result = in; // No shift
            3'b001: result = {in[7], 1'b0, in[6:1]}; // Shift right by 1 bit
            3'b010: result = {in[7], 2'b0, in[6:2]}; // Shift right by 2 bits
            3'b011: result = {in[7], 3'b0, in[6:3]}; // Shift right by 3 bits
            3'b100: result = {in[7], 4'b0, in[6:4]}; // Shift right by 4 bits
            3'b101: result = {in[7], 5'b0, in[6:5]}; // Shift right by 5 bits
            3'b110: result = {in[7], 6'b0, in[6]}; // Shift right by 6 bits
            3'b111: result = {in[7], 7'b0}; // Shift right by 7 bits
            default: result = in; // No shift (default case)
        endcase
    end

    // this will need 3 of 2to1 mux levels. so #1 for each and give #3 delay
    assign #3 out = result;

endmodule

module LeftRotate (
    in,
    out,
    shift
);

    input [7:0] in;
    input [2:0] shift;
    output [7:0] out;    

    reg [7:0] result;

    always @(*) begin
        case (shift)
            3'b000: result = in; // No rotate
            3'b001: result = {in[6:0], in[7]}; // rotate left by 1 bit
            3'b010: result = {in[5:0], in[7:6]}; // rotate left by 2 bits
            3'b011: result = {in[4:0], in[7:5]}; // rotate left by 3 bits
            3'b100: result = {in[3:0], in[7:4]}; // rotate left by 4 bits
            3'b101: result = {in[2:0], in[7:3]}; // rotate left by 5 bits
            3'b110: result = {in[1:0], in[7:2]}; // rotate left by 6 bits
            3'b111: result = {in[0], in[7:1]}; // rotate left by 7 bits
            default: result = in; // No rotate (default case)
        endcase
    end

    // this will need 3 of 2to1 mux levels. so #1 for each and give #3 delay
    assign #3 out = result;

endmodule

module RightRotate (
    in,
    out,
    shift
);

    input [7:0] in;
    input [2:0] shift;
    output [7:0] out;

    reg [7:0] result;

    always @(*) begin
        case (shift)
            3'b000: result = in; // No rotate
            3'b001: result = {in[0], in[7:1]}; // rotate right by 1 bit
            3'b010: result = {in[1:0], in[7:2]}; // rotate right by 2 bits
            3'b011: result = {in[2:0], in[7:3]}; // rotate right by 3 bits
            3'b100: result = {in[3:0], in[7:4]}; // rotate right by 4 bits
            3'b101: result = {in[4:0], in[7:5]}; // rotate right by 5 bits
            3'b110: result = {in[5:0], in[7:6]}; // rotate right by 6 bits
            3'b111: result = {in[6:0], in[7]}; // rotate right by 7 bits
            default: result = in; // No rotate (default case)
        endcase
    end

    // this will need 3 of 2to1 mux levels. so #1 for each and give #3 delay
    assign #3 out = result;

endmodule

module Shifter (
    out,
    in,
    im
);

    input [7:0] in, im;
    output reg [7:0] out;
    // im is the imidiate value in instruction
    wire [7:0] lshift,rshift,lshiftA,rshiftA,rrotate,lrotate;

    LeftShift ls(in,lshift,im[2:0]);
    RightShift rs(in,rshift,im[2:0]);
    LeftShiftArith lsa(in,lshiftA,im[2:0]);
    RightShiftArith rsa(in,rshiftA,im[2:0]);
    LeftRotate lr(in,lrotate,im[2:0]);
    RightRotate rr(in,rrotate,im[2:0]);

    always @(im) begin
        case (im[7:5])
            3'b000: assign out = lshift;
            3'b001: assign out = rshift;
            3'b010: assign out = lshiftA;
            3'b011: assign out = rshiftA;
            3'b100: assign out = lrotate;
            3'b101: assign out = rrotate;
            default assign out = im;
        endcase
    end    
    
endmodule

module ALU (
    DATA1,
    DATA2,
    RESULT,
    SELECT,
    ZERO
);
    // Define Inputs
    input [7:0] DATA1,DATA2;
    input [2:0] SELECT;
    // Define Output
    output reg [7:0] RESULT;
    wire [7:0] wire1,wire2,wire3,wire4,wire5,wire6,wire7,wire8;
    output reg ZERO;
    
    FORWARD forward1(DATA1,DATA2,wire1);            
    ADD add1(DATA1,DATA2,wire2);            
    AND and1(DATA1,DATA2,wire3);            
    OR or1(DATA1,DATA2,wire4); 
    Shifter shift(wire5,DATA1,DATA2);    

    always @(SELECT) begin
        case (SELECT)
            3'b000: assign RESULT = wire1;
            3'b001: assign RESULT = wire2;
            3'b010: assign RESULT = wire3;
            3'b011: assign RESULT = wire4;
            3'b100: assign RESULT = wire5;
        endcase
    end    

    always @(wire2) begin
        if(wire2 == 0)begin
            ZERO = 1;
        end
        else begin
            ZERO = 0;
        end
    end

endmodule

part2/reg.v
module reg_file(IN, OUT1, OUT2, INADDRESS, OUT1ADDRESS, OUT2ADDRESS, WRITE, CLK, RESET);
    // Declare input
    input [7:0] IN;
	input [2:0] INADDRESS, OUT1ADDRESS, OUT2ADDRESS;
	input WRITE, CLK, RESET;
    // Declare output
	output [7:0] OUT1, OUT2;
	
	
	
	// 8 x 8 register
	reg [7:0] REGISTER [7:0];

	//iterative variable
	integer i;
	
	
	//assigning the outputs
	assign #2 OUT1 = REGISTER[OUT1ADDRESS];		//assign the value that storesd in OUT1ADDRESS
	assign #2 OUT2 = REGISTER[OUT2ADDRESS];		//assign the value that storesd in OUT2ADDRESS
	
	
	always @ (posedge CLK)
	begin
		if (RESET == 1'b1)		
		begin		
			for (i = 0; i < 8; i = i + 1)			
			begin
				REGISTER[i] = 8'b00000000;		
			end			
		end
		else if (WRITE == 1'b1)			
		begin		
			#1 REGISTER[INADDRESS] = IN;			
		end		
	end	
endmodule

part5/cpu_tb.v
// Computer Architecture (CO224) - Lab 05
// Design: Testbench of Integrated CPU of Simple Processor
// Author: Isuru Nawinne

module cpu_tb;

    reg CLK, RESET;
    wire [31:0] PC;
    wire [31:0] INSTRUCTION;
    
    /* 
    ------------------------
     SIMPLE INSTRUCTION MEM
    ------------------------
    */
    
    // TODO: Initialize an array of registers (8x1024) named 'instr_mem' to be used as instruction memory
    reg [7:0] instr_mem [1023:0];
    
    // TODO: Create combinational logic to support CPU instruction fetching, given the Program Counter(PC) value 
    //       (make sure you include the delay for instruction fetching here)
    assign #2 INSTRUCTION = {instr_mem[PC+3], instr_mem[PC+2], instr_mem[PC+1], instr_mem[PC]};
    
    initial
    begin
        // Initialize instruction memory with the set of instructions you need execute on CPU
        
        // METHOD 1: manually loading instructions to instr_mem
        //{instr_mem[10'd3], instr_mem[10'd2], instr_mem[10'd1], instr_mem[10'd0]} = 32'b00000000000001000000000000000101;
        //{instr_mem[10'd7], instr_mem[10'd6], instr_mem[10'd5], instr_mem[10'd4]} = 32'b00000000000000100000000000001001;
        //{instr_mem[10'd11], instr_mem[10'd10], instr_mem[10'd9], instr_mem[10'd8]} = 32'b00000010000001100000010000000010;
        
        // METHOD 2: loading instr_mem content from instr_mem.mem file
        $readmemb("instr_mem.mem", instr_mem);
    end
    
    /* 
    -----
     CPU
    -----
    */
    cpu mycpu(PC, INSTRUCTION, CLK, RESET);

    initial
    begin
    
        // generate files needed to plot the waveform using GTKWave
        $dumpfile("cpu_wavedata.vcd");
		$dumpvars(0, cpu_tb);
        
        CLK = 1'b0;
        RESET = 1'b1;
        
        // TODO: Reset the CPU (by giving a pulse to RESET signal) to start the program execution
        #5
        RESET = 1'b0;
        // finish simulation after some time
        #500
        $finish;
        
    end
    
    // clock signal generation
    always
        #4 CLK = ~CLK;
        

endmodule

part5/cpu_wavedata.vcd
$date
	Mon May 06 15:58:19 2024
$end
$version
	Icarus Verilog
$end
$timescale
	1s
$end
$scope module cpu_tb $end
$var wire 32 ! PC [31:0] $end
$var wire 32 " INSTRUCTION [31:0] $end
$var reg 1 # CLK $end
$var reg 1 $ RESET $end
$scope module mycpu $end
$var wire 1 # CLK $end
$var wire 32 % INSTRUCTION [31:0] $end
$var wire 1 $ RESET $end
$var wire 1 & writeEn $end
$var wire 1 ' sourceSelect $end
$var wire 1 ( signSelect $end
$var wire 8 ) regout2 [7:0] $end
$var wire 8 * regout1 [7:0] $end
$var wire 1 + neqSelect $end
$var wire 8 , negOut [7:0] $end
$var wire 8 - muxSourceOut [7:0] $end
$var wire 8 . muxNegOut [7:0] $end
$var wire 32 / jumpedPC [31:0] $end
$var wire 1 0 jumpSelect $end
$var wire 32 1 finalPC [31:0] $end
$var wire 32 2 extendedValue [31:0] $end
$var wire 1 3 eqSelect $end
$var wire 1 4 Zero $end
$var wire 32 5 PCout [31:0] $end
$var wire 8 6 ALUres [7:0] $end
$var wire 3 7 ALUopcode [2:0] $end
$var reg 32 8 PC [31:0] $end
$scope module badder $end
$var wire 32 9 offset [31:0] $end
$var wire 32 : finalPC [31:0] $end
$var wire 32 ; currPC [31:0] $end
$upscope $end
$scope module control $end
$var wire 8 < opcode [7:0] $end
$var reg 3 = ALUOP [2:0] $end
$var reg 1 3 eqSelect $end
$var reg 1 0 jumpSelect $end
$var reg 1 + neqSelect $end
$var reg 1 ( signSelect $end
$var reg 1 ' sourceSelect $end
$var reg 1 & writeEn $end
$upscope $end
$scope module jump $end
$var wire 1 3 eqSelect $end
$var wire 32 > input2 [31:0] $end
$var wire 1 0 jumpSelect $end
$var wire 1 + neqselect $end
$var wire 32 ? input1 [31:0] $end
$var wire 1 4 Zero $end
$var reg 32 @ result [31:0] $end
$upscope $end
$scope module muxNeg $end
$var wire 1 ( select $end
$var wire 8 A input2 [7:0] $end
$var wire 8 B input1 [7:0] $end
$var reg 8 C result [7:0] $end
$upscope $end
$scope module muxSrc $end
$var wire 8 D input1 [7:0] $end
$var wire 8 E input2 [7:0] $end
$var wire 1 ' select $end
$var reg 8 F result [7:0] $end
$upscope $end
$scope module myalu $end
$var wire 8 G DATA2 [7:0] $end
$var wire 3 H SELECT [2:0] $end
$var wire 8 I wire5 [7:0] $end
$var wire 8 J wire4 [7:0] $end
$var wire 8 K wire3 [7:0] $end
$var wire 8 L wire2 [7:0] $end
$var wire 8 M wire1 [7:0] $end
$var wire 8 N DATA1 [7:0] $end
$var reg 8 O RESULT [7:0] $end
$var reg 1 4 ZERO $end
$scope module add1 $end
$var wire 8 P DATA2 [7:0] $end
$var wire 8 Q DATA1 [7:0] $end
$var reg 8 R RESULT [7:0] $end
$upscope $end
$scope module and1 $end
$var wire 8 S DATA2 [7:0] $end
$var wire 8 T DATA1 [7:0] $end
$var reg 8 U RESULT [7:0] $end
$upscope $end
$scope module forward1 $end
$var wire 8 V DATA2 [7:0] $end
$var wire 8 W DATA1 [7:0] $end
$var reg 8 X RESULT [7:0] $end
$upscope $end
$scope module or1 $end
$var wire 8 Y DATA2 [7:0] $end
$var wire 8 Z DATA1 [7:0] $end
$var reg 8 [ RESULT [7:0] $end
$upscope $end
$scope module shift $end
$var wire 8 \ im [7:0] $end
$var wire 8 ] rshiftA [7:0] $end
$var wire 8 ^ rshift [7:0] $end
$var wire 8 _ rrotate [7:0] $end
$var wire 8 ` lshiftA [7:0] $end
$var wire 8 a lshift [7:0] $end
$var wire 8 b lrotate [7:0] $end
$var wire 8 c in [7:0] $end
$var reg 8 d out [7:0] $end
$scope module lr $end
$var wire 8 e out [7:0] $end
$var wire 3 f shift [2:0] $end
$var wire 8 g in [7:0] $end
$var reg 8 h result [7:0] $end
$upscope $end
$scope module ls $end
$var wire 8 i out [7:0] $end
$var wire 3 j shift [2:0] $end
$var wire 8 k in [7:0] $end
$var reg 8 l result [7:0] $end
$upscope $end
$scope module lsa $end
$var wire 8 m out [7:0] $end
$var wire 3 n shift [2:0] $end
$var wire 8 o in [7:0] $end
$var reg 8 p result [7:0] $end
$upscope $end
$scope module rr $end
$var wire 8 q out [7:0] $end
$var wire 3 r shift [2:0] $end
$var wire 8 s in [7:0] $end
$var reg 8 t result [7:0] $end
$upscope $end
$scope module rs $end
$var wire 8 u out [7:0] $end
$var wire 3 v shift [2:0] $end
$var wire 8 w in [7:0] $end
$var reg 8 x result [7:0] $end
$upscope $end
$scope module rsa $end
$var wire 8 y out [7:0] $end
$var wire 3 z shift [2:0] $end
$var wire 8 { in [7:0] $end
$var reg 8 | result [7:0] $end
$upscope $end
$upscope $end
$upscope $end
$scope module neg $end
$var wire 8 } Output [7:0] $end
$var wire 8 ~ Input [7:0] $end
$upscope $end
$scope module pcadd $end
$var wire 32 !" PC [31:0] $end
$var wire 32 "" PCplus4 [31:0] $end
$upscope $end
$scope module register $end
$var wire 1 # CLK $end
$var wire 8 #" IN [7:0] $end
$var wire 3 $" INADDRESS [2:0] $end
$var wire 8 %" OUT1 [7:0] $end
$var wire 3 &" OUT1ADDRESS [2:0] $end
$var wire 8 '" OUT2 [7:0] $end
$var wire 3 (" OUT2ADDRESS [2:0] $end
$var wire 1 $ RESET $end
$var wire 1 & WRITE $end
$var integer 32 )" i [31:0] $end
$upscope $end
$scope module signext $end
$var wire 8 *" short [7:0] $end
$var wire 32 +" long [31:0] $end
$upscope $end
$upscope $end
$upscope $end
$enddefinitions $end
$comment Show the parameter values. $end
$dumpall
$end
#0
$dumpvars
bx00 +"
bx *"
bx )"
bx ("
bx '"
bx &"
bx %"
bx $"
bx #"
bx ""
bx !"
bx ~
bx }
bx |
bx {
bx z
bx y
bx x
bx w
bx v
bx u
bx t
bx s
bx r
bx q
bx p
bx o
bx n
bx m
bx l
bx k
bx j
bx i
bx h
bx g
bx f
bx e
bx d
bx c
bx b
bx a
bx `
bx _
bx ^
bx ]
bx \
bx [
bx Z
bx Y
bx X
bx W
bx V
bx U
bx T
bx S
bx R
bx Q
bx P
bx O
bx N
bx M
bx L
bx K
bx J
bx I
bx H
bx G
bx F
bx E
bx D
bx C
bx B
bx A
bx @
bx ?
bx >
bx =
bx <
bx ;
bx :
bx00 9
bx 8
bx 7
bx 6
bx 5
x4
x3
bx00 2
bx 1
x0
bx /
bx .
bx -
bx ,
x+
bx *
bx )
x(
x'
x&
bx %
1$
0#
bx "
bx !
$end
#4
b1000 )"
1#
#5
b100 1
b100 @
b100 5
b100 ;
b100 ?
b100 ""
b0 !
b0 8
b0 !"
0$
#7
b100 /
b100 :
b100 >
b0 2
b0 9
b0 +"
b0 <
b0 $"
b0 &"
b1 ("
b10000001 E
b0 *"
b10000001 "
b10000001 %
#8
bx0 l
b0xxxxxxx x
bx0 p
bx0xxxxxx |
b1 j
b1 v
b1 n
b1 z
b1 f
b1 r
b10000001 -
b10000001 F
b10000001 G
b10000001 P
b10000001 S
b10000001 V
b10000001 Y
b10000001 \
0+
03
00
1&
1'
0(
b0 7
b0 =
b0 H
0#
#9
b0 h
b0 l
b0 p
b0 t
b0 x
b0 |
b0 .
b0 C
b0 D
b10000001 J
b10000001 [
b0 K
b0 U
b10000001 6
b10000001 O
b10000001 #"
b10000001 M
b10000001 X
b0 *
b0 N
b0 Q
b0 T
b0 W
b0 Z
b0 c
b0 g
b0 k
b0 o
b0 s
b0 w
b0 {
b0 %"
b0 )
b0 B
b0 ~
b0 '"
#10
04
b0 ,
b0 A
b0 }
b10000001 L
b10000001 R
#12
b0 I
b0 d
b0 b
b0 e
b0 a
b0 i
b0 `
b0 m
b0 _
b0 q
b0 ^
b0 u
b0 ]
b0 y
1#
#13
b1000 1
b1000 @
b1000 /
b1000 :
b1000 >
b1000 5
b1000 ;
b1000 ?
b1000 ""
b100 !
b100 8
b100 !"
#15
b1 -
b1 F
b1 G
b1 P
b1 S
b1 V
b1 Y
b1 \
b1100 /
b1100 :
b1100 >
b100 2
b100 9
b100 +"
b11 h
b10 l
b10000010 p
b11000000 t
b1000000 x
b10000000 |
b1001 <
b1 $"
b1 E
b1 *"
b10000001 *
b10000001 N
b10000001 Q
b10000001 T
b10000001 W
b10000001 Z
b10000001 c
b10000001 g
b10000001 k
b10000001 o
b10000001 s
b10000001 w
b10000001 {
b10000001 %"
b1001000000010000000000000001 "
b1001000000010000000000000001 %
#16
b100 7
b100 =
b100 H
b0 6
b0 O
b0 #"
b1 M
b1 X
b1 K
b1 U
0#
#17
b10000010 L
b10000010 R
#18
b11 b
b11 e
b10 6
b10 O
b10 #"
b10 I
b10 d
b10 a
b10 i
b10000010 `
b10000010 m
b11000000 _
b11000000 q
b1000000 ^
b1000000 u
b10000000 ]
b10000000 y
#20
1#
#21
b1100 1
b1100 @
b10000 /
b10000 :
b10000 >
b1100 5
b1100 ;
b1100 ?
b1100 ""
b1000 !
b1000 8
b1000 !"
#23
b1000000 6
b1000000 O
b1000000 #"
b1000000 I
b1000000 d
b10100 /
b10100 :
b10100 >
b1000 2
b1000 9
b1000 +"
b100001 -
b100001 F
b100001 G
b100001 P
b100001 S
b100001 V
b100001 Y
b100001 \
b10 $"
b100001 E
b10 *"
b10 .
b10 C
b10 D
b1001000000100000000000100001 "
b1001000000100000000000100001 %
b10 )
b10 B
b10 ~
b10 '"
#24
b10100001 J
b10100001 [
b100001 M
b100001 X
b11111110 ,
b11111110 A
b11111110 }
0#
#25
b10100010 L
b10100010 R
#28
1#
#29
b10000 1
b10000 @
b11000 /
b11000 :
b11000 >
b10000 5
b10000 ;
b10000 ?
b10000 ""
b1100 !
b1100 8
b1100 !"
#31
b10000010 6
b10000010 O
b10000010 #"
b10000010 I
b10000010 d
b1000001 -
b1000001 F
b1000001 G
b1000001 P
b1000001 S
b1000001 V
b1000001 Y
b1000001 \
b11100 /
b11100 :
b11100 >
b1100 2
b1100 9
b1100 +"
b11 $"
b1000001 E
b11 *"
b1001000000110000000001000001 "
b1001000000110000000001000001 %
#32
b1000001 M
b1000001 X
b11000001 J
b11000001 [
0#
#33
b11000010 L
b11000010 R
#36
1#
#37
b10100 1
b10100 @
b100000 /
b100000 :
b100000 >
b10100 5
b10100 ;
b10100 ?
b10100 ""
b10000 !
b10000 8
b10000 !"
#39
b10000000 6
b10000000 O
b10000000 #"
b10000000 I
b10000000 d
b1100001 -
b1100001 F
b1100001 G
b1100001 P
b1100001 S
b1100001 V
b1100001 Y
b1100001 \
b100100 /
b100100 :
b100100 >
b10000 2
b10000 9
b10000 +"
b100 $"
b1100001 E
b100 *"
b1001000001000000000001100001 "
b1001000001000000000001100001 %
#40
b11100001 J
b11100001 [
b1100001 M
b1100001 X
0#
#41
b11100010 L
b11100010 R
#44
1#
#45
b11000 1
b11000 @
b101000 /
b101000 :
b101000 >
b11000 5
b11000 ;
b11000 ?
b11000 ""
b10100 !
b10100 8
b10100 !"
#47
b11 6
b11 O
b11 #"
b11 I
b11 d
b10000001 -
b10000001 F
b10000001 G
b10000001 P
b10000001 S
b10000001 V
b10000001 Y
b10000001 \
b101100 /
b101100 :
b101100 >
b10100 2
b10100 9
b10100 +"
b101 $"
b10000001 E
b101 *"
b1001000001010000000010000001 "
b1001000001010000000010000001 %
#48
b10000001 M
b10000001 X
b10000001 K
b10000001 U
b10000001 J
b10000001 [
0#
#49
b10 L
b10 R
#52
1#
#53
b11100 1
b11100 @
b110000 /
b110000 :
b110000 >
b11100 5
b11100 ;
b11100 ?
b11100 ""
b11000 !
b11000 8
b11000 !"
#55
b11000000 6
b11000000 O
b11000000 #"
b11000000 I
b11000000 d
b10100001 -
b10100001 F
b10100001 G
b10100001 P
b10100001 S
b10100001 V
b10100001 Y
b10100001 \
b110100 /
b110100 :
b110100 >
b11000 2
b11000 9
b11000 +"
b110 $"
b10100001 E
b110 *"
b1001000001100000000010100001 "
b1001000001100000000010100001 %
#56
b10100001 J
b10100001 [
b10100001 M
b10100001 X
0#
#57
b100010 L
b100010 R
#60
1#
#61
b100000 1
b100000 @
b111000 /
b111000 :
b111000 >
b100000 5
b100000 ;
b100000 ?
b100000 ""
b11100 !
b11100 8
b11100 !"
#63
b10000001 l
b10000001 x
b10000001 p
b10000001 |
b10000001 h
b10000001 t
b10 6
b10 O
b10 #"
b10 I
b10 d
b0 j
b0 v
b0 n
b0 z
b0 f
b0 r
b0 -
b0 F
b0 G
b0 P
b0 S
b0 V
b0 Y
b0 \
b100000 /
b100000 :
b100000 >
b0 2
b0 9
b0 +"
b10 <
b0 $"
b0 ("
b0 E
b0 *"
b10000000000000000000000000 "
b10000000000000000000000000 %
#64
b100 l
b100000 x
b10000100 p
b10000000 |
b110 h
b1100000 t
b10 j
b10 v
b10 n
b10 z
b10 f
b10 r
b10 -
b10 F
b10 G
b10 P
b10 S
b10 V
b10 Y
b10 \
b100010 6
b100010 O
b100010 #"
b0 M
b0 X
b0 K
b0 U
b10000001 J
b10000001 [
0'
b1 7
b1 =
b1 H
0#
