part4/cpu.v
// Control Unit
module ControlUnit (
    opcode,
    signSelect,
    sourceSelect,
    jumpSelect,
    eqSelect,
    ALUOP,
    writeEn
);
    // opcode
    input [7:0] opcode;
    // signselect for sub and source select for imidiate, register
    output reg signSelect,sourceSelect,jumpSelect,eqSelect;
    // op-code for alu
    output reg [2:0] ALUOP;
    output reg writeEn;

    always @(opcode) begin
        // Loadi 
        if (opcode == 8'b00000000) begin
            #1
            ALUOP = 3'b000;
            signSelect = 1'b0;
            sourceSelect = 1'b1;
            writeEn = 1'b1;
            jumpSelect = 1'b0;
            eqSelect = 1'b0;
        // mov
        end else if (opcode == 8'b00000001) begin
            #1
            ALUOP = 3'b000;
            signSelect = 1'b0;
            sourceSelect = 1'b0;
            writeEn = 1'b1;
            jumpSelect = 1'b0;
            eqSelect = 1'b0;
        // add
        end else if (opcode == 8'b00000010) begin
            #1
            ALUOP = 3'b001;
            signSelect = 1'b0;
            sourceSelect = 1'b0;
            writeEn = 1'b1;
            jumpSelect = 1'b0;
            eqSelect = 1'b0;
        // sub
        end else if (opcode == 8'b00000011) begin
            #1
            ALUOP = 3'b001;
            signSelect = 1'b1;
            sourceSelect = 1'b0;
            writeEn = 1'b1;
            jumpSelect = 1'b0;
            eqSelect = 1'b0;
        // and
        end else if (opcode == 8'b00000100) begin
            #1
            ALUOP = 3'b010;
            signSelect = 1'b0;
            sourceSelect = 1'b0;
            writeEn = 1'b1;
            jumpSelect = 1'b0;
            eqSelect = 1'b0;
        // or
        end else if (opcode == 8'b00000101) begin
            #1
            ALUOP = 3'b011;
            signSelect = 1'b0;
            sourceSelect = 1'b0;
            writeEn = 1'b1;
            jumpSelect = 1'b0;
            eqSelect = 1'b0;
        // j
        end else if (opcode == 8'b00000110) begin
            #1
            ALUOP = 3'b000;
            signSelect = 1'b0;
            sourceSelect = 1'b0;
            writeEn = 1'b0;
            jumpSelect = 1'b1;
            eqSelect = 1'b0;
        // beq
        end else if (opcode == 8'b00000111) begin
            #1
            ALUOP = 3'b111;
            signSelect = 1'b1;
            sourceSelect = 1'b0;
            writeEn = 1'b0;
            jumpSelect = 1'b0;
            eqSelect = 1'b1;
        end else begin
            
        end
    end
    
endmodule

// Program Counter
module pcAdder(PC, PCplus4);
	
	//Declaration of input and output ports
	input [31:0] PC;
	output [31:0] PCplus4;

	//Assign PC+4 value to the output after 1 time unit delay
	assign PCplus4 = PC + 4;
	
endmodule

// module negation
module Negator (
    Input,
    Output
);

input [7:0] Input;
output [7:0] Output;

assign #1 Output = ~Input + 8'b00000001;
    
endmodule

module mux (
    input1,
    input2,
    result,
    select
);

input [7:0] input1,input2;
output reg [7:0] result;
input select;

always @(*) begin
    if (select) begin
        result = input2;
    end else begin
        result = input1;
    end
end
    
endmodule

module muxPC (
    input1,
    input2,
    result,
    select1,
    select2,
    select3
);

input [31:0] input1,input2;
output reg [31:0] result;
input select1,select2,select3;

always @(*) begin
    if (select1 || select2 && select3) begin
        result = input2;
    end else begin
        result = input1;
    end
end
    
endmodule

// branch adder
module branchAdder (
    currPC,
    offset,
    finalPC
);

input [31:0] currPC, offset;
output [31:0] finalPC;

assign finalPC = currPC + offset;
    
endmodule

// sign extender
module SignExtender (
    short,
    long
);

input [7:0] short;
output [31:0] long;

assign long = {{24{short[7]}}, short} << 2;
    
endmodule

// Main CPU module
module cpu (
    PC,
    INSTRUCTION,
    CLK,
    RESET
);

// Instruction input
input [31:0] INSTRUCTION;
// input clock and reset
input CLK,RESET;
// output pc to get instruction
output reg [31:0] PC;
wire [31:0] PCout;
// Wires for sign and source select
wire signSelect, sourceSelect, jumpSelect, eqSelect;
// Alu opcode wire
wire [2:0] ALUopcode;
// wire for alu result, regout1 and regout2
wire [7:0] ALUres,regout1,regout2;
// mux outputs
wire [7:0] muxNegOut,muxSourceOut;
// negator out
wire [7:0] negOut;
// wire for write enable
wire writeEn;
// wire reg add in
wire [2:0] readreg1,readreg2;
// Extended value
wire [31:0] extendedValue;
// Jumped pc value
wire [31:0] jumpedPC, finalPC;
// alu zero output
wire Zero;

// instantiate control module
ControlUnit control(INSTRUCTION[31:24],signSelect,sourceSelect,jumpSelect,eqSelect,ALUopcode,writeEn);
reg_file register(ALUres,regout1,regout2,INSTRUCTION[18:16],INSTRUCTION[10:8],INSTRUCTION[2:0],writeEn,CLK,RESET);
ALU myalu(regout1,muxSourceOut,ALUres,ALUopcode,Zero);
Negator neg(regout2,negOut);    
mux muxSrc(muxNegOut,INSTRUCTION[7:0],muxSourceOut,sourceSelect);
mux muxNeg(regout2,negOut,muxNegOut,signSelect);
pcAdder pcadd(PC,PCout);
branchAdder badder(PCout, extendedValue, jumpedPC);
SignExtender signext(INSTRUCTION[23:16], extendedValue);
muxPC jump(PCout, jumpedPC, finalPC, jumpSelect, Zero, eqSelect);

always @ (posedge CLK)
	begin
		if (RESET == 1'b1) 
		begin
			#1
			PC = 0;		//If RESET signal is HIGH, set PC to zero
		end
		else #1 PC = finalPC;		//Else, write new PC value
	end

endmodule

part4/alu.v
// Forward Function
module FORWARD (
    DATA1,
    DATA2,
    RESULT
);
    // Define Inputs
    input [7:0] DATA1, DATA2;
    // Define Outputs
    output reg [7:0] RESULT;

    always @(DATA1, DATA2) begin
        #1
        RESULT = DATA2; 
    end
    
endmodule


// bitvise AND
module AND (
    DATA1,
    DATA2,
    RESULT
);

    // Define Inputs
    input [7:0] DATA1, DATA2;
    // Define Outputs
    output reg [7:0] RESULT;

    always @(DATA1, DATA2) begin  
        #1      
        RESULT = DATA1 & DATA2;
    end
    
endmodule

// Bitwise OR
module OR (
    DATA1,
    DATA2,
    RESULT
);

    // Define Inputs
    input [7:0] DATA1, DATA2;
    // Define Outputs
    output reg [7:0] RESULT;

    always @(DATA1, DATA2) begin
        #1
        RESULT = DATA1 | DATA2;
    end
    
endmodule

// Module ADD
module ADD (
    DATA1,
    DATA2,
    RESULT
);

    // Define Inputs
    input [7:0] DATA1, DATA2;
    // Define Outputs
    output reg [7:0] RESULT;

    always @(DATA1, DATA2) begin
        #2
        RESULT = DATA1 + DATA2;
    end
    
endmodule

module ALU (
    DATA1,
    DATA2,
    RESULT,
    SELECT,
    ZERO
);
    // Define Inputs
    input [7:0] DATA1,DATA2;
    input [2:0] SELECT;
    // Define Output
    output reg [7:0] RESULT;
    wire [7:0] wire1,wire2,wire3,wire4;
    output reg ZERO;
    
    FORWARD forward1(DATA1,DATA2,wire1);            
    ADD add1(DATA1,DATA2,wire2);            
    AND and1(DATA1,DATA2,wire3);            
    OR or1(DATA1,DATA2,wire4);  

    always @(SELECT) begin
        case (SELECT)
            3'b000: assign RESULT = wire1;
            3'b001: assign RESULT = wire2;
            3'b010: assign RESULT = wire3;
            3'b011: assign RESULT = wire4;
        endcase
    end    

    always @(wire2) begin
        if(wire2 == 0)begin
            ZERO = 1;
        end
        else begin
            ZERO = 0;
        end
    end

endmodule

part4/reg.v
module reg_file(IN, OUT1, OUT2, INADDRESS, OUT1ADDRESS, OUT2ADDRESS, WRITE, CLK, RESET);
    // Declare input
    input [7:0] IN;
	input [2:0] INADDRESS, OUT1ADDRESS, OUT2ADDRESS;
	input WRITE, CLK, RESET;
    // Declare output
	output [7:0] OUT1, OUT2;
	
	
	
	// 8 x 8 register
	reg [7:0] REGISTER [7:0];

	//iterative variable
	integer i;
	
	
	//assigning the outputs
	assign #2 OUT1 = REGISTER[OUT1ADDRESS];		//assign the value that storesd in OUT1ADDRESS
	assign #2 OUT2 = REGISTER[OUT2ADDRESS];		//assign the value that storesd in OUT2ADDRESS
	
	
	always @ (posedge CLK)
	begin
		if (RESET == 1'b1)		
		begin		
			for (i = 0; i < 8; i = i + 1)			
			begin
				REGISTER[i] = 8'b00000000;		
			end			
		end
		else if (WRITE == 1'b1)			
		begin		
			#1 REGISTER[INADDRESS] = IN;			
		end		
	end	
    initial begin
	    $monitor($time, "\t%d\t%d\t%d\t%d\t%d\t%d\t%d\t%d", REGISTER[0], REGISTER[1],REGISTER[2],REGISTER[3],REGISTER[4],REGISTER[5],REGISTER[6],REGISTER[7]);        
    end
endmodule

part5/cpu_tb.v
// Computer Architecture (CO224) - Lab 05
// Design: Testbench of Integrated CPU of Simple Processor
// Author: Isuru Nawinne

module cpu_tb;

    reg CLK, RESET;
    wire [31:0] PC;
    wire [31:0] INSTRUCTION;
    
    /* 
    ------------------------
     SIMPLE INSTRUCTION MEM
    ------------------------
    */
    
    // TODO: Initialize an array of registers (8x1024) named 'instr_mem' to be used as instruction memory
    reg [7:0] instr_mem [1023:0];
    
    // TODO: Create combinational logic to support CPU instruction fetching, given the Program Counter(PC) value 
    //       (make sure you include the delay for instruction fetching here)
    assign #2 INSTRUCTION = {instr_mem[PC+3], instr_mem[PC+2], instr_mem[PC+1], instr_mem[PC]};
    
    initial
    begin
        // Initialize instruction memory with the set of instructions you need execute on CPU
        
        // METHOD 1: manually loading instructions to instr_mem
        //{instr_mem[10'd3], instr_mem[10'd2], instr_mem[10'd1], instr_mem[10'd0]} = 32'b00000000000001000000000000000101;
        //{instr_mem[10'd7], instr_mem[10'd6], instr_mem[10'd5], instr_mem[10'd4]} = 32'b00000000000000100000000000001001;
        //{instr_mem[10'd11], instr_mem[10'd10], instr_mem[10'd9], instr_mem[10'd8]} = 32'b00000010000001100000010000000010;
        
        // METHOD 2: loading instr_mem content from instr_mem.mem file
        $readmemb("instr_mem.mem", instr_mem);
    end
    
    /* 
    -----
     CPU
    -----
    */
    cpu mycpu(PC, INSTRUCTION, CLK, RESET);

    initial
    begin
    
        // generate files needed to plot the waveform using GTKWave
        $dumpfile("cpu_wavedata.vcd");
		$dumpvars(0, cpu_tb);
        
        CLK = 1'b0;
        RESET = 1'b1;
        
        // TODO: Reset the CPU (by giving a pulse to RESET signal) to start the program execution
        #5
        RESET = 1'b0;
        // finish simulation after some time
        #500
        $finish;
        
    end
    
    // clock signal generation
    always
        #4 CLK = ~CLK;
        

endmodule

part4/cpu_wavedata.vcd
$date
	Wed May 31 10:36:26 2023
$end
$version
	Icarus Verilog
$end
$timescale
	1s
$end
$scope module cpu_tb $end
$var wire 32 ! PC [31:0] $end
$var wire 32 " INSTRUCTION [31:0] $end
$var reg 1 # CLK $end
$var reg 1 $ RESET $end
$scope module mycpu $end
$var wire 1 # CLK $end
$var wire 32 % INSTRUCTION [31:0] $end
$var wire 1 $ RESET $end
$var wire 1 & writeEn $end
$var wire 1 ' sourceSelect $end
$var wire 1 ( signSelect $end
$var wire 8 ) regout2 [7:0] $end
$var wire 8 * regout1 [7:0] $end
$var wire 8 + negOut [7:0] $end
$var wire 8 , muxSourceOut [7:0] $end
$var wire 8 - muxNegOut [7:0] $end
$var wire 32 . jumpedPC [31:0] $end
$var wire 1 / jumpSelect $end
$var wire 32 0 finalPC [31:0] $end
$var wire 32 1 extendedValue [31:0] $end
$var wire 1 2 eqSelect $end
$var wire 1 3 Zero $end
$var wire 32 4 PCout [31:0] $end
$var wire 8 5 ALUres [7:0] $end
$var wire 3 6 ALUopcode [2:0] $end
$var reg 32 7 PC [31:0] $end
$scope module badder $end
$var wire 32 8 offset [31:0] $end
$var wire 32 9 finalPC [31:0] $end
$var wire 32 : currPC [31:0] $end
$upscope $end
$scope module control $end
$var wire 8 ; opcode [7:0] $end
$var reg 3 < ALUOP [2:0] $end
$var reg 1 2 eqSelect $end
$var reg 1 / jumpSelect $end
$var reg 1 ( signSelect $end
$var reg 1 ' sourceSelect $end
$var reg 1 & writeEn $end
$upscope $end
$scope module jump $end
$var wire 32 = input2 [31:0] $end
$var wire 1 / select1 $end
$var wire 1 2 select3 $end
$var wire 1 3 select2 $end
$var wire 32 > input1 [31:0] $end
$var reg 32 ? result [31:0] $end
$upscope $end
$scope module muxNeg $end
$var wire 1 ( select $end
$var wire 8 @ input2 [7:0] $end
$var wire 8 A input1 [7:0] $end
$var reg 8 B result [7:0] $end
$upscope $end
$scope module muxSrc $end
$var wire 8 C input1 [7:0] $end
$var wire 8 D input2 [7:0] $end
$var wire 1 ' select $end
$var reg 8 E result [7:0] $end
$upscope $end
$scope module myalu $end
$var wire 8 F DATA2 [7:0] $end
$var wire 3 G SELECT [2:0] $end
$var wire 8 H wire4 [7:0] $end
$var wire 8 I wire3 [7:0] $end
$var wire 8 J wire2 [7:0] $end
$var wire 8 K wire1 [7:0] $end
$var wire 8 L DATA1 [7:0] $end
$var reg 8 M RESULT [7:0] $end
$var reg 1 3 ZERO $end
$scope module add1 $end
$var wire 8 N DATA2 [7:0] $end
$var wire 8 O DATA1 [7:0] $end
$var reg 8 P RESULT [7:0] $end
$upscope $end
$scope module and1 $end
$var wire 8 Q DATA2 [7:0] $end
$var wire 8 R DATA1 [7:0] $end
$var reg 8 S RESULT [7:0] $end
$upscope $end
$scope module forward1 $end
$var wire 8 T DATA2 [7:0] $end
$var wire 8 U DATA1 [7:0] $end
$var reg 8 V RESULT [7:0] $end
$upscope $end
$scope module or1 $end
$var wire 8 W DATA2 [7:0] $end
$var wire 8 X DATA1 [7:0] $end
$var reg 8 Y RESULT [7:0] $end
$upscope $end
$upscope $end
$scope module neg $end
$var wire 8 Z Output [7:0] $end
$var wire 8 [ Input [7:0] $end
$upscope $end
$scope module pcadd $end
$var wire 32 \ PC [31:0] $end
$var wire 32 ] PCplus4 [31:0] $end
$upscope $end
$scope module register $end
$var wire 1 # CLK $end
$var wire 8 ^ IN [7:0] $end
$var wire 3 _ INADDRESS [2:0] $end
$var wire 8 ` OUT1 [7:0] $end
$var wire 3 a OUT1ADDRESS [2:0] $end
$var wire 8 b OUT2 [7:0] $end
$var wire 3 c OUT2ADDRESS [2:0] $end
$var wire 1 $ RESET $end
$var wire 1 & WRITE $end
$var integer 32 d i [31:0] $end
$upscope $end
$scope module signext $end
$var wire 8 e short [7:0] $end
$var wire 32 f long [31:0] $end
$upscope $end
$upscope $end
$upscope $end
$enddefinitions $end
#0
$dumpvars
bx00 f
bx e
bx d
bx c
bx b
bx a
bx `
bx _
bx ^
bx ]
bx \
bx [
bx Z
bx Y
bx X
bx W
bx V
bx U
bx T
bx S
bx R
bx Q
bx P
bx O
bx N
bx M
bx L
bx K
bx J
bx I
bx H
bx G
bx F
bx E
bx D
bx C
bx B
bx A
bx @
bx ?
bx >
bx =
bx <
bx ;
bx :
bx 9
bx00 8
bx 7
bx 6
bx 5
bx 4
x3
x2
bx00 1
bx 0
x/
bx .
bx -
bx ,
bx +
bx *
bx )
x(
x'
x&
bx %
1$
0#
bx "
bx !
$end
#4
b1000 d
1#
#5
b100 0
b100 ?
b100 4
b100 :
b100 >
b100 ]
b0 !
b0 7
b0 \
0$
#7
b1000 .
b1000 9
b1000 =
b100 1
b100 8
b100 f
b0 ;
b1 _
b0 a
b1 c
b1 D
b1 e
b10000000000000001 "
b10000000000000001 %
#8
b1 ,
b1 E
b1 F
b1 N
b1 Q
b1 T
b1 W
02
0/
1&
1'
0(
b0 6
b0 <
b0 G
0#
#9
b0 -
b0 B
b0 C
b1 H
b1 Y
b0 I
b0 S
b1 5
b1 M
b1 ^
b1 K
b1 V
b0 *
b0 L
b0 O
b0 R
b0 U
b0 X
b0 `
b0 )
b0 A
b0 [
b0 b
#10
03
b0 +
b0 @
b0 Z
b1 J
b1 P
#12
1#
#13
b1000 0
b1000 ?
b1100 .
b1100 9
b1100 =
b1000 4
b1000 :
b1000 >
b1000 ]
b100 !
b100 7
b100 \
#15
b10000 .
b10000 9
b10000 =
b1000 1
b1000 8
b1000 f
b1 -
b1 B
b1 C
b1 ;
b10 _
b10 e
b1 )
b1 A
b1 [
b1 b
b1000000100000000000000001 "
b1000000100000000000000001 %
#16
0'
b11111111 +
b11111111 @
b11111111 Z
0#
#20
1#
#21
b1100 0
b1100 ?
b10100 .
b10100 9
b10100 =
b1100 4
b1100 :
b1100 >
b1100 ]
b1000 !
b1000 7
b1000 \
#23
b11100 .
b11100 9
b11100 =
b10000 1
b10000 8
b10000 f
b100 _
b100 e
b1000001000000000000000001 "
b1000001000000000000000001 %
#24
0#
#28
1#
#29
b10000 0
b10000 ?
b100000 .
b100000 9
b100000 =
b10000 4
b10000 :
b10000 >
b10000 ]
b1100 !
b1100 7
b1100 \
#31
b11100 .
b11100 9
b11100 =
b1100 1
b1100 8
b1100 f
b0 ;
b11 _
b110 c
b110 D
b11 e
b110000000000000110 "
b110000000000000110 %
#32
b110 ,
b110 E
b110 F
b110 N
b110 Q
b110 T
b110 W
1'
0#
#33
b0 -
b0 B
b0 C
b110 5
b110 M
b110 ^
b110 K
b110 V
b110 H
b110 Y
b0 )
b0 A
b0 [
b0 b
#34
b0 +
b0 @
b0 Z
b110 J
b110 P
#36
1#
#37
b10100 0
b10100 ?
b100000 .
b100000 9
b100000 =
b10100 4
b10100 :
b10100 >
b10100 ]
b10000 !
b10000 7
b10000 \
#39
b11 ,
b11 E
b11 F
b11 N
b11 Q
b11 T
b11 W
b100100 .
b100100 9
b100100 =
b10000 1
b10000 8
b10000 f
b111 ;
b100 _
b11 c
b11 D
b100 e
b111000001000000000000000011 "
b111000001000000000000000011 %
#40
b0 ,
b0 E
b0 F
b0 N
b0 Q
b0 T
b0 W
b11 H
b11 Y
b11 5
b11 M
b11 ^
b11 K
b11 V
12
0&
0'
1(
b111 6
b111 <
b111 G
0#
#41
b100100 0
b100100 ?
13
b0 5
b0 M
b0 ^
b0 K
b0 V
b0 H
b0 Y
b0 J
b0 P
b110 )
b110 A
b110 [
b110 b
#42
b11111010 ,
b11111010 E
b11111010 F
b11111010 N
b11111010 Q
b11111010 T
b11111010 W
b11111010 -
b11111010 B
b11111010 C
b11111010 +
b11111010 @
b11111010 Z
#43
b11111010 H
b11111010 Y
b11111010 5
b11111010 M
b11111010 ^
b11111010 K
b11111010 V
#44
b10100 0
b10100 ?
03
b11111010 J
b11111010 P
1#
#45
b11000 0
b11000 ?
b101000 .
b101000 9
b101000 =
b11000 4
b11000 :
b11000 >
b11000 ]
b10100 !
b10100 7
b10100 \
#47
b11000 .
b11000 9
b11000 =
b0 1
b0 8
b0 f
b10 ;
b0 _
b10 c
b10 D
b0 e
b10000000000000000000000010 "
b10000000000000000000000010 %
#48
b110 ,
b110 E
b110 F
b110 N
b110 Q
b110 T
b110 W
b110 -
b110 B
b110 C
02
1&
0(
b1 6
b1 <
b1 G
0#
#49
b1 ,
b1 E
b1 F
b1 N
b1 Q
b1 T
b1 W
b1 -
b1 B
b1 C
b110 K
b110 V
b110 H
b110 Y
b1 )
b1 A
b1 [
b1 b
#50
b1 H
b1 Y
b1 K
b1 V
b11111111 +
b11111111 @
b11111111 Z
b1 5
b1 M
b1 ^
b1 J
b1 P
#52
1#
#53
b11100 0
b11100 ?
b11100 .
b11100 9
b11100 =
b11100 4
b11100 :
b11100 >
b11100 ]
b11000 !
b11000 7
b11000 \
#55
b100000 .
b100000 9
b100000 =
b100 1
b100 8
b100 f
b1 _
b1 a
b100 c
b100 D
b1 e
b1 *
b1 L
b1 O
b1 R
b1 U
b1 X
b1 `
b10000000010000000100000100 "
b10000000010000000100000100 %
#56
b1 I
b1 S
0#
#57
b10 5
b10 M
b10 ^
b10 J
b10 P
#60
1#
#61
b100000 0
b100000 ?
b100100 .
b100100 9
b100100 =
b100000 4
b100000 :
b100000 >
b100000 ]
b11100 !
b11100 7
b11100 \
#63
b110000 .
b110000 9
b110000 =
b10000 1
b10000 8
b10000 f
b1 ;
b100 _
b0 a
b1 c
b1 D
b100 e
b1000001000000000000000001 "
b1000001000000000000000001 %
b10 *
b10 L
b10 O
b10 R
b10 U
b10 X
b10 `
#64
b1 5
b1 M
b1 ^
b0 6
b0 <
b0 G
b11 H
b11 Y
b0 I
b0 S
0#
#65
b10 ,
b10 E
b10 F
b10 N
b10 Q
b10 T
b10 W
b10 -
b10 B
b10 C
b1 *
b1 L
b1 O
b1 R
b1 U
b1 X
b1 `
b10 )
b10 A
b10 [
b10 b
b11 J
b11 P
#66
b10 5
b10 M
b10 ^
b10 K
b10 V
b11111110 +
b11111110 @
b11111110 Z
#68
1#
#69
b100100 0
b100100 ?
b110100 .
b110100 9
b110100 =
b100100 4
b100100 :
b100100 >
b100100 ]
b100000 !
b100000 7
b100000 \
#71
b1100 .
b1100 9
b1100 =
b11111111111111111111111111101000 1
b11111111111111111111111111101000 8
b11111111111111111111111111101000 f
b110 ;
b10 _
b0 c
b0 D
b11111010 e
b110111110100000000000000000 "
b110111110100000000000000000 %
#72
b1100 0
b1100 ?
1/
0&
0#
#73
b1 ,
b1 E
b1 F
b1 N
b1 Q
b1 T
b1 W
b1 -
b1 B
b1 C
b1 )
b1 A
b1 [
b1 b
#74
b1 H
b1 Y
b1 I
b1 S
b1 5
b1 M
b1 ^
b1 K
b1 V
b11111111 +
b11111111 @
b11111111 Z
#75
b10 J
b10 P
#76
1#
#77
b11111111111111111111111111111000 0
b11111111111111111111111111111000 ?
b11111111111111111111111111111000 .
b11111111111111111111111111111000 9
b11111111111111111111111111111000 =
b10000 4
b10000 :
b10000 >
b10000 ]
b1100 !
b1100 7
b1100 \
#79
b11100 0
b11100 ?
b11100 .
b11100 9
b11100 =
b1100 1
b1100 8
b1100 f
b0 ;
b11 _
b110 c
b110 D
b11 e
b110000000000000110 "
b110000000000000110 %
#80
b10000 0
b10000 ?
b110 ,
b110 E
b110 F
b110 N
b110 Q
b110 T
b110 W
0/
1&
1'
0#
#81
b0 -
b0 B
b0 C
b110 5
b110 M
b110 ^
b110 K
b110 V
b0 I
b0 S
b111 H
b111 Y
b0 )
b0 A
b0 [
b0 b
#82
b0 +
b0 @
b0 Z
b111 J
b111 P
#84
1#
#85
b10100 0
b10100 ?
b100000 .
b100000 9
b100000 =
b10100 4
b10100 :
b10100 >
b10100 ]
b10000 !
b10000 7
b10000 \
#87
b11 ,
b11 E
b11 F
b11 N
b11 Q
b11 T
b11 W
b100100 .
b100100 9
b100100 =
b10000 1
b10000 8
b10000 f
b111 ;
b100 _
b11 c
b11 D
b100 e
b111000001000000000000000011 "
b111000001000000000000000011 %
#88
b0 ,
b0 E
b0 F
b0 N
b0 Q
b0 T
b0 W
b11 H
b11 Y
b1 I
b1 S
b11 5
b11 M
b11 ^
b11 K
b11 V
12
0&
0'
1(
b111 6
b111 <
b111 G
0#
#89
b0 5
b0 M
b0 ^
b0 K
b0 V
b0 I
b0 S
b1 H
b1 Y
b1 J
b1 P
b110 )
b110 A
b110 [
b110 b
#90
b11111010 ,
b11111010 E
b11111010 F
b11111010 N
b11111010 Q
b11111010 T
b11111010 W
b11111010 -
b11111010 B
b11111010 C
b11111010 +
b11111010 @
b11111010 Z
#91
b11111011 H
b11111011 Y
b11111010 5
b11111010 M
b11111010 ^
b11111010 K
b11111010 V
#92
b11111011 J
b11111011 P
1#
#93
b11000 0
b11000 ?
b101000 .
b101000 9
b101000 =
b11000 4
b11000 :
b11000 >
b11000 ]
b10100 !
b10100 7
b10100 \
#95
b11000 .
b11000 9
b11000 =
b0 1
b0 8
b0 f
b10 ;
b0 _
b10 c
b10 D
b0 e
b10000000000000000000000010 "
b10000000000000000000000010 %
#96
b110 ,
b110 E
b110 F
b110 N
b110 Q
b110 T
b110 W
b110 -
b110 B
b110 C
b11111011 5
b11111011 M
b11111011 ^
02
1&
0(
b1 6
b1 <
b1 G
0#
#97
b1 ,
b1 E
b1 F
b1 N
b1 Q
b1 T
b1 W
b1 -
b1 B
b1 C
b110 K
b110 V
b111 H
b111 Y
b1 )
b1 A
b1 [
b1 b
#98
b1 H
b1 Y
b1 I
b1 S
b1 K
b1 V
b11111111 +
b11111111 @
b11111111 Z
b10 5
b10 M
b10 ^
b10 J
b10 P
#100
1#
#101
b11100 0
b11100 ?
b11100 .
b11100 9
b11100 =
b11100 4
b11100 :
b11100 >
b11100 ]
b11000 !
b11000 7
b11000 \
#103
b100000 .
b100000 9
b100000 =
b100 1
b100 8
b100 f
b1 _
b1 a
b100 c
b100 D
b1 e
b10 *
b10 L
b10 O
b10 R
b10 U
b10 X
b10 `
b10000000010000000100000100 "
b10000000010000000100000100 %
#104
b0 I
b0 S
b11 H
b11 Y
0#
#105
b10 ,
b10 E
b10 F
b10 N
b10 Q
b10 T
b10 W
b10 -
b10 B
b10 C
b11 5
b11 M
b11 ^
b11 J
b11 P
b10 )
b10 A
b10 [
b10 b
#106
b10 H
b10 Y
b10 I
b10 S
b10 K
b10 V
b11111110 +
b11111110 @
b11111110 Z
#107
b100 5
b100 M
b100 ^
b100 J
b100 P
#108
1#
#109
b100000 0
b100000 ?
b100100 .
b100100 9
b100100 =
b100000 4
b100000 :
b100000 >
b100000 ]
b11100 !
b11100 7
b11100 \
#111
b110000 .
b110000 9
b110000 =
b10000 1
b10000 8
b10000 f
b1 ;
b100 _
b0 a
b1 c
b1 D
b100 e
b1000001000000000000000001 "
b1000001000000000000000001 %
b100 *
b100 L
b100 O
b100 R
b100 U
b100 X
b100 `
#112
b10 5
b10 M
b10 ^
b0 6
b0 <
b0 G
b0 I
b0 S
b110 H
b110 Y
0#
#113
b100 ,
b100 E
b100 F
b100 N
b100 Q
b100 T
b100 W
b100 -
b100 B
b100 C
b10 *
b10 L
b10 O
b10 R
b10 U
b10 X
b10 `
b100 )
b100 A
b100 [
b100 b
b110 J
b110 P
#114
b100 5
b100 M
b100 ^
b100 K
b100 V
b11111100 +
b11111100 @
b11111100 Z
#116
1#
#117
b100100 0
b100100 ?
b110100 .
b110100 9
b110100 =
b100100 4
b100100 :
b100100 >
b100100 ]
b100000 !
b100000 7
b100000 \
#119
b1100 .
b1100 9
b1100 =
b11111111111111111111111111101000 1
b11111111111111111111111111101000 8
b11111111111111111111111111101000 f
b110 ;
b10 _
b0 c
b0 D
b11111010 e
b110111110100000000000000000 "
b110111110100000000000000000 %
#120
b1100 0
b1100 ?
1/
0&
0#
#121
b10 ,
b10 E
b10 F
b10 N
b10 Q
b10 T
b10 W
b10 -
b10 B
b10 C
b10 )
b10 A
b10 [
b10 b
#122
b10 5
b10 M
b10 ^
b10 K
b10 V
b10 I
b10 S
b10 H
b10 Y
b11111110 +
b11111110 @
b11111110 Z
#123
b100 J
b100 P
#124
1#
#125
b11111111111111111111111111111000 0
b11111111111111111111111111111000 ?
b11111111111111111111111111111000 .
b11111111111111111111111111111000 9
b11111111111111111111111111111000 =
b10000 4
b10000 :
b10000 >
b10000 ]
b1100 !
b1100 7
b1100 \
#127
b11100 0
b11100 ?
b11100 .
b11100 9
b11100 =
b1100 1
b1100 8
b1100 f
b0 ;
b11 _
b110 c
b110 D
b11 e
b110000000000000110 "
b110000000000000110 %
#128
b10000 0
b10000 ?
b110 ,
b110 E
b110 F
b110 N
b110 Q
b110 T
b110 W
0/
1&
1'
0#
#129
b0 -
b0 B
b0 C
b110 H
b110 Y
b110 5
b110 M
b110 ^
b110 K
b110 V
b0 )
b0 A
b0 [
b0 b
#130
b0 +
b0 @
b0 Z
b1000 J
b1000 P
#132
1#
#133
b10100 0
b10100 ?
b100000 .
b100000 9
b100000 =
b10100 4
b10100 :
b10100 >
b10100 ]
b10000 !
b10000 7
b10000 \
#135
b11 ,
b11 E
b11 F
b11 N
b11 Q
b11 T
b11 W
b100100 .
b100100 9
b100100 =
b10000 1
b10000 8
b10000 f
b111 ;
b100 _
b11 c
b11 D
b100 e
b111000001000000000000000011 "
b111000001000000000000000011 %
#136
b0 ,
b0 E
b0 F
b0 N
b0 Q
b0 T
b0 W
b11 5
b11 M
b11 ^
b11 K
b11 V
b11 H
b11 Y
12
0&
0'
1(
b111 6
b111 <
b111 G
0#
#137
b10 H
b10 Y
b0 I
b0 S
b0 5
b0 M
b0 ^
b0 K
b0 V
b10 J
b10 P
b110 )
b110 A
b110 [
b110 b
#138
b11111010 ,
b11111010 E
b11111010 F
b11111010 N
b11111010 Q
b11111010 T
b11111010 W
b11111010 -
b11111010 B
b11111010 C
b11111010 +
b11111010 @
b11111010 Z
#139
b11111010 5
b11111010 M
b11111010 ^
b11111010 K
b11111010 V
b10 I
b10 S
b11111010 H
b11111010 Y
#140
b11111100 J
b11111100 P
1#
#141
b11000 0
b11000 ?
b101000 .
b101000 9
b101000 =
b11000 4
b11000 :
b11000 >
b11000 ]
b10100 !
b10100 7
b10100 \
#143
b11000 .
b11000 9
b11000 =
b0 1
b0 8
b0 f
b10 ;
b0 _
b10 c
b10 D
b0 e
b10000000000000000000000010 "
b10000000000000000000000010 %
#144
b110 ,
b110 E
b110 F
b110 N
b110 Q
b110 T
b110 W
b110 -
b110 B
b110 C
b11111100 5
b11111100 M
b11111100 ^
02
1&
0(
b1 6
b1 <
b1 G
0#
#145
b1 ,
b1 E
b1 F
b1 N
b1 Q
b1 T
b1 W
b1 -
b1 B
b1 C
b110 H
b110 Y
b110 K
b110 V
b1 )
b1 A
b1 [
b1 b
#146
b1 K
b1 V
b0 I
b0 S
b11 H
b11 Y
b11111111 +
b11111111 @
b11111111 Z
b11 5
b11 M
b11 ^
b11 J
b11 P
#148
1#
#149
b11100 0
b11100 ?
b11100 .
b11100 9
b11100 =
b11100 4
b11100 :
b11100 >
b11100 ]
b11000 !
b11000 7
b11000 \
#151
b100000 .
b100000 9
b100000 =
b100 1
b100 8
b100 f
b1 _
b1 a
b100 c
b100 D
b1 e
b11 *
b11 L
b11 O
b11 R
b11 U
b11 X
b11 `
b10000000010000000100000100 "
b10000000010000000100000100 %
#152
b1 I
b1 S
0#
#153
b100 ,
b100 E
b100 F
b100 N
b100 Q
b100 T
b100 W
b100 -
b100 B
b100 C
b101 5
b101 M
b101 ^
b101 J
b101 P
b100 *
b100 L
b100 O
b100 R
b100 U
b100 X
b100 `
b100 )
b100 A
b100 [
b100 b
#154
b100 K
b100 V
b100 I
b100 S
b100 H
b100 Y
b11111100 +
b11111100 @
b11111100 Z
